streamsight/__init__.py
streamsight/algorithms/__init__.py
streamsight/algorithms/base.py
streamsight/algorithms/decay_popularity.py
streamsight/algorithms/itemknn.py
streamsight/algorithms/itemknn_incremental.py
streamsight/algorithms/itemknn_incremental_movielens.py
streamsight/algorithms/itemknn_rolling.py
streamsight/algorithms/itemknn_static.py
streamsight/algorithms/most_pop.py
streamsight/algorithms/random.py
streamsight/algorithms/recent_popularity.py
streamsight/algorithms/time_aware_item_knn/__init__.py
streamsight/algorithms/time_aware_item_knn/base.py
streamsight/algorithms/time_aware_item_knn/decay_functions.py
streamsight/algorithms/time_aware_item_knn/ding_2005.py
streamsight/algorithms/time_aware_item_knn/liu_2010.py
streamsight/algorithms/time_aware_item_knn/similarity_functions.py
streamsight/algorithms/time_aware_item_knn/top_k.py
streamsight/algorithms/time_aware_item_knn/utils.py
streamsight/algorithms/time_aware_item_knn/vaz_2013.py
streamsight/algorithms/utils.py
streamsight/datasets/__init__.py
streamsight/datasets/base.py
streamsight/datasets/config/__init__.py
streamsight/datasets/config/amazon.py
streamsight/datasets/config/base.py
streamsight/datasets/config/lastfm.py
streamsight/datasets/config/movielens.py
streamsight/datasets/config/yelp.py
streamsight/datasets/datasets/__init__.py
streamsight/datasets/datasets/amazon.py
streamsight/datasets/datasets/base.py
streamsight/datasets/datasets/lastfm.py
streamsight/datasets/datasets/movielens.py
streamsight/datasets/datasets/test.py
streamsight/datasets/datasets/yelp.py
streamsight/datasets/metadata/__init__.py
streamsight/datasets/metadata/amazon.py
streamsight/datasets/metadata/base.py
streamsight/datasets/metadata/lastfm.py
streamsight/datasets/metadata/movielens.py
streamsight/evaluators/__init__.py
streamsight/evaluators/accumulator.py
streamsight/evaluators/base.py
streamsight/evaluators/builder/__init__.py
streamsight/evaluators/builder/base.py
streamsight-3.1.7.dist-info/WHEEL
streamsight-3.1.7.dist-info/METADATA
streamsight-3.1.7.dist-info/RECORD
