Metadata-Version: 2.3
Name: streamsight
Version: 3.1.7
Summary: A toolkit for offline evaluation of Recommender Systems.
Keywords: recsys,recommendation,practical evaluation,global timeline,reccomender systems,data leakage
Author: Ng Tze Kean
Author-email: Ng Tze Kean <ngtzekean@gmail.com>
Requires-Dist: colorama>=0.4.6
Requires-Dist: colorlog>=6.10.1
Requires-Dist: deprecation>=2.1.0
Requires-Dist: httpx>=0.28.1
Requires-Dist: numpy==2.2.6
Requires-Dist: pandas>=2.3.3
Requires-Dist: progressbar>=2.5
Requires-Dist: pyarrow>=22.0.0
Requires-Dist: pyfiglet>=1.0.4
Requires-Dist: scikit-learn>=1.7.2
Requires-Dist: scipy>=1.16.3
Requires-Dist: simplejson>=3.20.2
Requires-Dist: tqdm>=4.67.1
Requires-Dist: typing-extensions>=4.15.0
Requires-Dist: urllib3>=2.5.0
Maintainer: Ng Tze Kean
Maintainer-email: Ng Tze Kean <ngtzekean@gmail.com>
Requires-Python: >=3.13
Project-URL: Homepage, https://hiiamtzekean.github.io/streamsight/
Project-URL: Repository, https://github.com/ngtzekean/streamsight
